{
  "Tuesday May 5, 2026": false,
  "Thursday May 7, 2026": false,
  "Tuesday May 12, 2026": false,
  "Tuesday May 19, 2026": false,
  "Thursday May 21, 2026": false,
  "Tuesday May 26, 2026": false,
  "Thursday May 28, 2026": false,
  "Tuesday June 2, 2026": false,
  "Thursday June 4, 2026": false,
  "Tuesday June 9, 2026": false,
  "Thursday June 11, 2026": false,
  "Tuesday June 16, 2026": true,
  "Thursday June 18, 2026": false,
  "Tuesday June 23, 2026": false,
  "Thursday June 25, 2026": false
}